just_because/__init__.py
just_because/ji.py
just_because/ji2zhiyin.py
just_because/patterns.py
just_because/requirements.txt
just_because/zhiyin.py
just_because/zhiyin2ji.py
just_because/words/ji.txt
just_because/words/yin.txt
just_because/words/zhi.txt
just_because-1.0.2.dist-info/LICENSE
just_because-1.0.2.dist-info/METADATA
just_because-1.0.2.dist-info/WHEEL
just_because-1.0.2.dist-info/top_level.txt
just_because-1.0.2.dist-info/RECORD
