Metadata-Version: 2.1
Name: just-because
Version: 1.0.2
Summary: 鸡你太美
Home-page: https://github.com/zqmillet/just-because
Author: ikun
Author-email: zqmillet@qq.com
License: UNKNOWN
Platform: UNKNOWN
License-File: LICENSE
